11_vcd/LEDFLASH.v
`timescale 1 ns / 1 ns

module LEDFLASH (
  input  		i_SCLK,
  input  		i_RESET_SYSB,
  input  		i_PMOD1_P1,
  output [3:0]  o_LED
  );
// =======================  
  reg  [3:0] LED_COUNT;
  reg         PULSE;
// =======================
  always @(posedge i_SCLK or negedge i_RESET_SYSB)
	if( ~i_RESET_SYSB )
		PULSE <= 0;
	else
        PULSE <= i_PMOD1_P1;

  always @(posedge i_SCLK or negedge i_RESET_SYSB)
	if( ~i_RESET_SYSB )
		LED_COUNT <= 0;
	else if( PULSE )
        LED_COUNT <= LED_COUNT + 1;

  assign o_LED[3:0] = LED_COUNT[3:0];	// connects led outputs to counter value

endmodule

13_vcd/tb_LEDFLASH.v
`timescale 1 ns / 1 ns

module tb_LEDFLASH;

reg             SCLK;
reg             PMOD1_P1;
reg             RESET_SYSB;
wire    [3:0]   LED;

LEDFLASH LD(
        .i_SCLK  	  (SCLK),
        .i_PMOD1_P1   (PMOD1_P1),
		.i_RESET_SYSB (RESET_SYSB),
        .o_LED        (LED)
        );

initial
begin
    SCLK 		= 1'b0;
	RESET_SYSB  = 1'b0;
    PMOD1_P1 	= 1'b1;
end

always
    #0.5 SCLK = ~SCLK;

initial
begin
    #2  RESET_SYSB  = 1'b1;
    #10 PMOD1_P1	= 1'b0;
    #13 PMOD1_P1	= 1'b1;
    #40 PMOD1_P1	= 1'b0;
    #43 PMOD1_P1	= 1'b1;
    #70 PMOD1_P1	= 1'b0;
    #73 PMOD1_P1	= 1'b1;
	#10 $finish;
end

initial
begin
    $dumpfile("out.vcd");
    $dumpvars(0, LD);
end

endmodule

14_vcd/out.vcd
$date
	Fri Sep 25 16:13:42 2020
$end
$version
	Icarus Verilog
$end
$timescale
	1ns
$end
$scope module tb_LEDFLASH $end
$scope module LD $end
$var wire 1 ! i_PMOD1_P1 $end
$var wire 1 " i_RESET_SYSB $end
$var wire 1 # i_SCLK $end
$var wire 4 $ o_LED [3:0] $end
$var reg 4 % LED_COUNT [3:0] $end
$var reg 1 & PULSE $end
$upscope $end
$upscope $end
$enddefinitions $end
#0
$dumpvars
0&
b0 %
b0 $
0#
0"
1!
$end
#1
1#
#2
0#
1"
#3
1&
1#
#4
0#
#5
b1 $
b1 %
1#
#6
0#
#7
b10 $
b10 %
1#
#8
0#
#9
b11 $
b11 %
1#
#10
0#
#11
b100 $
b100 %
1#
#12
0#
0!
#13
b101 $
b101 %
0&
1#
#14
0#
#15
1#
#16
0#
#17
1#
#18
0#
#19
1#
#20
0#
#21
1#
#22
0#
#23
1#
#24
0#
#25
1&
1#
1!
#26
0#
#27
b110 $
b110 %
1#
#28
0#
#29
b111 $
b111 %
1#
#30
0#
#31
b1000 $
b1000 %
1#
#32
0#
#33
b1001 $
b1001 %
1#
#34
0#
#35
b1010 $
b1010 %
1#
#36
0#
#37
b1011 $
b1011 %
1#
#38
0#
#39
b1100 $
b1100 %
1#
#40
0#
#41
b1101 $
b1101 %
1#
#42
0#
#43
b1110 $
b1110 %
1#
#44
0#
#45
b1111 $
b1111 %
1#
#46
0#
#47
b0 $
b0 %
1#
#48
0#
#49
b1 $
b1 %
1#
#50
0#
#51
b10 $
b10 %
1#
#52
0#
#53
b11 $
b11 %
1#
#54
0#
#55
b100 $
b100 %
1#
#56
0#
#57
b101 $
b101 %
1#
#58
0#
#59
b110 $
b110 %
1#
#60
0#
#61
b111 $
b111 %
1#
#62
0#
#63
b1000 $
b1000 %
1#
#64
0#
#65
b1001 $
b1001 %
0&
1#
0!
